prismboost/__init__.py
prismboost-0.0.1.dist-info/METADATA
prismboost-0.0.1.dist-info/WHEEL
prismboost-0.0.1.dist-info/top_level.txt
prismboost-0.0.1.dist-info/RECORD
