Metadata-Version: 2.4
Name: prismboost
Version: 0.0.1
Summary: Geometry-boosted machine learning for industrial diagnostics. PRISM behavioral features + XGBoost.
Author-email: Jason Rudder <jason.rudder@protonmail.com>
License: MIT
Project-URL: Homepage, https://github.com/prism-engines/prismboost
Project-URL: Repository, https://github.com/prism-engines/prismboost
Keywords: machine-learning,predictive-maintenance,xgboost,industrial-diagnostics,rul-prediction
Classifier: Development Status :: 2 - Pre-Alpha
Classifier: Intended Audience :: Science/Research
Classifier: License :: OSI Approved :: MIT License
Classifier: Programming Language :: Python :: 3
Classifier: Programming Language :: Python :: 3.8
Classifier: Programming Language :: Python :: 3.9
Classifier: Programming Language :: Python :: 3.10
Classifier: Programming Language :: Python :: 3.11
Classifier: Programming Language :: Python :: 3.12
Classifier: Topic :: Scientific/Engineering
Classifier: Topic :: Scientific/Engineering :: Artificial Intelligence
Requires-Python: >=3.8
